{
    "backend": "api-server-nodejs",
    "db_name": "",
    "db_pass": "",
    "db_type": "sqlite",
    "db_user": "",
    "dbms": "1",
    "description": "generated product",
    "design": "berry-dashboard",
    "docker": "0",
    "err_code": 0,
    "frontend": "react",
    "heroku": "0",
    "pattern": "fullstack",
    "pro": "0",
    "task_id": "68461bd4-4ef0-4b93-a78e-dfc899f327ab",
    "task_info": "Upload Sources [0%] - 144 files",
    "task_output": "68461bd4-4ef0-4b93-a78e-dfc899f327ab.zip",
    "task_result": "SUCCESS",
    "task_state": "RUNNING",
    "task_ts_end": "2023-05-14-01-13-15",
    "task_ts_start": "2023-05-14-01-13-13"
}